Workbook

Sheet PyG
A1: Cuenta de pérdidas y ganancias 2025
A2: Talleres Martínez S.L. · Importes en euros
A4: Concepto | B4: T1 | C4: T2 | D4: T3 | E4: T4 | F4: Total 2025 | G4: % s/ ventas
A5: Importe neto de la cifra de negocios | B5: =SUMIFS(Diario!$E$2:$E$373,Diario!$F$2:$F$373,$A5,Diario!$H$2:$H$373,B$4) -> 69007.29 | C5: =SUMIFS(Diario!$E$2:$E$373,Diario!$F$2:$F$373,$A5,Diario!$H$2:$H$373,C$4) -> 70028.64 | D5: =SUMIFS(Diario!$E$2:$E$373,Diario!$F$2:$F$373,$A5,Diario!$H$2:$H$373,D$4) -> 70882.74 | E5: =SUMIFS(Diario!$E$2:$E$373,Diario!$F$2:$F$373,$A5,Diario!$H$2:$H$373,E$4) -> 79187.5 | F5: =SUM(B5:E5) -> 289106.17 | G5: =IF($F$5=0,0,F5/$F$5) -> 1
A6: Aprovisionamientos | B6: =-SUMIFS(Diario!$E$2:$E$373,Diario!$F$2:$F$373,$A6,Diario!$H$2:$H$373,B$4) -> -25677.54 | C6: =-SUMIFS(Diario!$E$2:$E$373,Diario!$F$2:$F$373,$A6,Diario!$H$2:$H$373,C$4) -> -23370.13 | D6: =-SUMIFS(Diario!$E$2:$E$373,Diario!$F$2:$F$373,$A6,Diario!$H$2:$H$373,D$4) -> -23596.22 | E6: =-SUMIFS(Diario!$E$2:$E$373,Diario!$F$2:$F$373,$A6,Diario!$H$2:$H$373,E$4) -> -25526.13 | F6: =SUM(B6:E6) -> -98170.02 | G6: =IF($F$5=0,0,F6/$F$5) -> -0.3395639
A7: Gastos de personal | B7: =-SUMIFS(Diario!$E$2:$E$373,Diario!$F$2:$F$373,$A7,Diario!$H$2:$H$373,B$4) -> -57450 | C7: =-SUMIFS(Diario!$E$2:$E$373,Diario!$F$2:$F$373,$A7,Diario!$H$2:$H$373,C$4) -> -57450 | D7: =-SUMIFS(Diario!$E$2:$E$373,Diario!$F$2:$F$373,$A7,Diario!$H$2:$H$373,D$4) -> -57450 | E7: =-SUMIFS(Diario!$E$2:$E$373,Diario!$F$2:$F$373,$A7,Diario!$H$2:$H$373,E$4) -> -57450 | F7: =SUM(B7:E7) -> -229800 | G7: =IF($F$5=0,0,F7/$F$5) -> -0.7948637
A8: Otros gastos de explotación | B8: =-SUMIFS(Diario!$E$2:$E$373,Diario!$F$2:$F$373,$A8,Diario!$H$2:$H$373,B$4) -> -12883.14 | C8: =-SUMIFS(Diario!$E$2:$E$373,Diario!$F$2:$F$373,$A8,Diario!$H$2:$H$373,C$4) -> -13073.98 | D8: =-SUMIFS(Diario!$E$2:$E$373,Diario!$F$2:$F$373,$A8,Diario!$H$2:$H$373,D$4) -> -12181.14 | E8: =-SUMIFS(Diario!$E$2:$E$373,Diario!$F$2:$F$373,$A8,Diario!$H$2:$H$373,E$4) -> -12310 | F8: =SUM(B8:E8) -> -50448.26 | G8: =IF($F$5=0,0,F8/$F$5) -> -0.17449735
A9: EBITDA | B9: =SUM(B5:B8) -> -27003.39 | C9: =SUM(C5:C8) -> -23865.47 | D9: =SUM(D5:D8) -> -22344.62 | E9: =SUM(E5:E8) -> -16098.63 | F9: =SUM(B9:E9) -> -89312.11 | G9: =IF($F$5=0,0,F9/$F$5) -> -0.30892495
A10: Amortización del inmovilizado | B10: =-SUMIFS(Diario!$E$2:$E$373,Diario!$F$2:$F$373,$A10,Diario!$H$2:$H$373,B$4) -> -3750 | C10: =-SUMIFS(Diario!$E$2:$E$373,Diario!$F$2:$F$373,$A10,Diario!$H$2:$H$373,C$4) -> -3750 | D10: =-SUMIFS(Diario!$E$2:$E$373,Diario!$F$2:$F$373,$A10,Diario!$H$2:$H$373,D$4) -> -3750 | E10: =-SUMIFS(Diario!$E$2:$E$373,Diario!$F$2:$F$373,$A10,Diario!$H$2:$H$373,E$4) -> -3750 | F10: =SUM(B10:E10) -> -15000 | G10: =IF($F$5=0,0,F10/$F$5) -> -0.051884054
A11: Resultado de explotación | B11: =B9+B10 -> -30753.39 | C11: =C9+C10 -> -27615.47 | D11: =D9+D10 -> -26094.62 | E11: =E9+E10 -> -19848.63 | F11: =SUM(B11:E11) -> -104312.11 | G11: =IF($F$5=0,0,F11/$F$5) -> -0.36080901
A12: Gastos financieros | B12: =-SUMIFS(Diario!$E$2:$E$373,Diario!$F$2:$F$373,$A12,Diario!$H$2:$H$373,B$4) -> -1163.29 | C12: =-SUMIFS(Diario!$E$2:$E$373,Diario!$F$2:$F$373,$A12,Diario!$H$2:$H$373,C$4) -> -1054.11 | D12: =-SUMIFS(Diario!$E$2:$E$373,Diario!$F$2:$F$373,$A12,Diario!$H$2:$H$373,D$4) -> -1390.45 | E12: =-SUMIFS(Diario!$E$2:$E$373,Diario!$F$2:$F$373,$A12,Diario!$H$2:$H$373,E$4) -> -1100.66 | F12: =SUM(B12:E12) -> -4708.51 | G12: =IF($F$5=0,0,F12/$F$5) -> -0.016286439
A13: Resultado antes de impuestos | B13: =B11+B12 -> -31916.68 | C13: =C11+C12 -> -28669.58 | D13: =D11+D12 -> -27485.07 | E13: =E11+E12 -> -20949.29 | F13: =SUM(B13:E13) -> -109020.62 | G13: =IF($F$5=0,0,F13/$F$5) -> -0.37709545
A14: Impuesto sobre beneficios (25 %) | B14: =-ROUND(MAX(0,B13)*25%,2) -> 0 | C14: =-ROUND(MAX(0,C13)*25%,2) -> 0 | D14: =-ROUND(MAX(0,D13)*25%,2) -> 0 | E14: =-ROUND(MAX(0,E13)*25%,2) -> 0 | F14: =SUM(B14:E14) -> 0 | G14: =IF($F$5=0,0,F14/$F$5) -> 0
A15: Resultado del ejercicio | B15: =B13+B14 -> -31916.68 | C15: =C13+C14 -> -28669.58 | D15: =D13+D14 -> -27485.07 | E15: =E13+E14 -> -20949.29 | F15: =SUM(B15:E15) -> -109020.62 | G15: =IF($F$5=0,0,F15/$F$5) -> -0.37709545
A17: Detalle por cuenta
A18: Código | B18: Cuenta | C18: Grupo | D18: Total | E18: Nº apuntes | F18: Media | G18: Máximo
A19: 700 | B19: =INDEX('Plan contable'!$B$2:$B$16,MATCH(A19,'Plan contable'!$A$2:$A$16,0)) -> Ventas de mercaderías | C19: {=_xlfn.XLOOKUP(A19,'Plan contable'!$A$2:$A$16,'Plan contable'!$C$2:$C$16,"Sin grupo")} -> Importe neto de la cifra de negocios | D19: =SUMIF(Diario!$C$2:$C$373,A19,Diario!$E$2:$E$373) -> 218140.53 | E19: =COUNTIF(Diario!$C$2:$C$373,A19) -> 72 | F19: =IFERROR(AVERAGEIF(Diario!$C$2:$C$373,A19,Diario!$E$2:$E$373),0) -> 3029.7296 | G19: =_xlfn.MAXIFS(Diario!$E$2:$E$373,Diario!$C$2:$C$373,A19) -> 4329.45
A20: 705 | B20: =INDEX('Plan contable'!$B$2:$B$16,MATCH(A20,'Plan contable'!$A$2:$A$16,0)) -> Prestaciones de servicios | C20: {=_xlfn.XLOOKUP(A20,'Plan contable'!$A$2:$A$16,'Plan contable'!$C$2:$C$16,"Sin grupo")} -> Importe neto de la cifra de negocios | D20: =SUMIF(Diario!$C$2:$C$373,A20,Diario!$E$2:$E$373) -> 70965.64 | E20: =COUNTIF(Diario!$C$2:$C$373,A20) -> 60 | F20: =IFERROR(AVERAGEIF(Diario!$C$2:$C$373,A20,Diario!$E$2:$E$373),0) -> 1182.7607 | G20: =_xlfn.MAXIFS(Diario!$E$2:$E$373,Diario!$C$2:$C$373,A20) -> 1757.27
A21: 600 | B21: =INDEX('Plan contable'!$B$2:$B$16,MATCH(A21,'Plan contable'!$A$2:$A$16,0)) -> Compras de mercaderías | C21: {=_xlfn.XLOOKUP(A21,'Plan contable'!$A$2:$A$16,'Plan contable'!$C$2:$C$16,"Sin grupo")} -> Aprovisionamientos | D21: =SUMIF(Diario!$C$2:$C$373,A21,Diario!$E$2:$E$373) -> 81102.85 | E21: =COUNTIF(Diario!$C$2:$C$373,A21) -> 60 | F21: =IFERROR(AVERAGEIF(Diario!$C$2:$C$373,A21,Diario!$E$2:$E$373),0) -> 1351.7142 | G21: =_xlfn.MAXIFS(Diario!$E$2:$E$373,Diario!$C$2:$C$373,A21) -> 2145.84
A22: 607 | B22: =INDEX('Plan contable'!$B$2:$B$16,MATCH(A22,'Plan contable'!$A$2:$A$16,0)) -> Trabajos realizados por otras empresas | C22: {=_xlfn.XLOOKUP(A22,'Plan contable'!$A$2:$A$16,'Plan contable'!$C$2:$C$16,"Sin grupo")} -> Aprovisionamientos | D22: =SUMIF(Diario!$C$2:$C$373,A22,Diario!$E$2:$E$373) -> 17067.17 | E22: =COUNTIF(Diario!$C$2:$C$373,A22) -> 24 | F22: =IFERROR(AVERAGEIF(Diario!$C$2:$C$373,A22,Diario!$E$2:$E$373),0) -> 711.13208 | G22: =_xlfn.MAXIFS(Diario!$E$2:$E$373,Diario!$C$2:$C$373,A22) -> 1233.36
A23: 640 | B23: =INDEX('Plan contable'!$B$2:$B$16,MATCH(A23,'Plan contable'!$A$2:$A$16,0)) -> Sueldos y salarios | C23: {=_xlfn.XLOOKUP(A23,'Plan contable'!$A$2:$A$16,'Plan contable'!$C$2:$C$16,"Sin grupo")} -> Gastos de personal | D23: =SUMIF(Diario!$C$2:$C$373,A23,Diario!$E$2:$E$373) -> 174000 | E23: =COUNTIF(Diario!$C$2:$C$373,A23) -> 12 | F23: =IFERROR(AVERAGEIF(Diario!$C$2:$C$373,A23,Diario!$E$2:$E$373),0) -> 14500 | G23: =_xlfn.MAXIFS(Diario!$E$2:$E$373,Diario!$C$2:$C$373,A23) -> 14500
A24: 642 | B24: =INDEX('Plan contable'!$B$2:$B$16,MATCH(A24,'Plan contable'!$A$2:$A$16,0)) -> Seguridad Social a cargo de la empresa | C24: {=_xlfn.XLOOKUP(A24,'Plan contable'!$A$2:$A$16,'Plan contable'!$C$2:$C$16,"Sin grupo")} -> Gastos de personal | D24: =SUMIF(Diario!$C$2:$C$373,A24,Diario!$E$2:$E$373) -> 55800 | E24: =COUNTIF(Diario!$C$2:$C$373,A24) -> 12 | F24: =IFERROR(AVERAGEIF(Diario!$C$2:$C$373,A24,Diario!$E$2:$E$373),0) -> 4650 | G24: =_xlfn.MAXIFS(Diario!$E$2:$E$373,Diario!$C$2:$C$373,A24) -> 4650
A25: 621 | B25: =INDEX('Plan contable'!$B$2:$B$16,MATCH(A25,'Plan contable'!$A$2:$A$16,0)) -> Arrendamientos y cánones | C25: {=_xlfn.XLOOKUP(A25,'Plan contable'!$A$2:$A$16,'Plan contable'!$C$2:$C$16,"Sin grupo")} -> Otros gastos de explotación | D25: =SUMIF(Diario!$C$2:$C$373,A25,Diario!$E$2:$E$373) -> 21600 | E25: =COUNTIF(Diario!$C$2:$C$373,A25) -> 12 | F25: =IFERROR(AVERAGEIF(Diario!$C$2:$C$373,A25,Diario!$E$2:$E$373),0) -> 1800 | G25: =_xlfn.MAXIFS(Diario!$E$2:$E$373,Diario!$C$2:$C$373,A25) -> 1800
A26: 622 | B26: =INDEX('Plan contable'!$B$2:$B$16,MATCH(A26,'Plan contable'!$A$2:$A$16,0)) -> Reparaciones y conservación | C26: {=_xlfn.XLOOKUP(A26,'Plan contable'!$A$2:$A$16,'Plan contable'!$C$2:$C$16,"Sin grupo")} -> Otros gastos de explotación | D26: =SUMIF(Diario!$C$2:$C$373,A26,Diario!$E$2:$E$373) -> 6710.53 | E26: =COUNTIF(Diario!$C$2:$C$373,A26) -> 12 | F26: =IFERROR(AVERAGEIF(Diario!$C$2:$C$373,A26,Diario!$E$2:$E$373),0) -> 559.21083 | G26: =_xlfn.MAXIFS(Diario!$E$2:$E$373,Diario!$C$2:$C$373,A26) -> 876.05
A27: 623 | B27: =INDEX('Plan contable'!$B$2:$B$16,MATCH(A27,'Plan contable'!$A$2:$A$16,0)) -> Servicios de profesionales independientes | C27: {=_xlfn.XLOOKUP(A27,'Plan contable'!$A$2:$A$16,'Plan contable'!$C$2:$C$16,"Sin grupo")} -> Otros gastos de explotación | D27: =SUMIF(Diario!$C$2:$C$373,A27,Diario!$E$2:$E$373) -> 4750.7 | E27: =COUNTIF(Diario!$C$2:$C$373,A27) -> 12 | F27: =IFERROR(AVERAGEIF(Diario!$C$2:$C$373,A27,Diario!$E$2:$E$373),0) -> 395.89167 | G27: =_xlfn.MAXIFS(Diario!$E$2:$E$373,Diario!$C$2:$C$373,A27) -> 538.83
A28: 625 | B28: =INDEX('Plan contable'!$B$2:$B$16,MATCH(A28,'Plan contable'!$A$2:$A$16,0)) -> Primas de seguros | C28: {=_xlfn.XLOOKUP(A28,'Plan contable'!$A$2:$A$16,'Plan contable'!$C$2:$C$16,"Sin grupo")} -> Otros gastos de explotación | D28: =SUMIF(Diario!$C$2:$C$373,A28,Diario!$E$2:$E$373) -> 2160 | E28: =COUNTIF(Diario!$C$2:$C$373,A28) -> 12 | F28: =IFERROR(AVERAGEIF(Diario!$C$2:$C$373,A28,Diario!$E$2:$E$373),0) -> 180 | G28: =_xlfn.MAXIFS(Diario!$E$2:$E$373,Diario!$C$2:$C$373,A28) -> 180
A29: 627 | B29: =INDEX('Plan contable'!$B$2:$B$16,MATCH(A29,'Plan contable'!$A$2:$A$16,0)) -> Publicidad, propaganda y relaciones públicas | C29: {=_xlfn.XLOOKUP(A29,'Plan contable'!$A$2:$A$16,'Plan contable'!$C$2:$C$16,"Sin grupo")} -> Otros gastos de explotación | D29: =SUMIF(Diario!$C$2:$C$373,A29,Diario!$E$2:$E$373) -> 6227.16 | E29: =COUNTIF(Diario!$C$2:$C$373,A29) -> 12 | F29: =IFERROR(AVERAGEIF(Diario!$C$2:$C$373,A29,Diario!$E$2:$E$373),0) -> 518.93 | G29: =_xlfn.MAXIFS(Diario!$E$2:$E$373,Diario!$C$2:$C$373,A29) -> 1154.96
A30: 628 | B30: =INDEX('Plan contable'!$B$2:$B$16,MATCH(A30,'Plan contable'!$A$2:$A$16,0)) -> Suministros | C30: {=_xlfn.XLOOKUP(A30,'Plan contable'!$A$2:$A$16,'Plan contable'!$C$2:$C$16,"Sin grupo")} -> Otros gastos de explotación | D30: =SUMIF(Diario!$C$2:$C$373,A30,Diario!$E$2:$E$373) -> 6597.15 | E30: =COUNTIF(Diario!$C$2:$C$373,A30) -> 24 | F30: =IFERROR(AVERAGEIF(Diario!$C$2:$C$373,A30,Diario!$E$2:$E$373),0) -> 274.88125 | G30: =_xlfn.MAXIFS(Diario!$E$2:$E$373,Diario!$C$2:$C$373,A30) -> 379.75
... A33: 662 | B33: =INDEX('Plan contable'!$B$2:$B$16,MATCH(A33,'Plan contable'!$A$2:$A$16,0)) -> Intereses de deudas | C33: {=_xlfn.XLOOKUP(A33,'Plan contable'!$A$2:$A$16,'Plan contable'!$C$2:$C$16,"Sin grupo")} -> Gastos financieros | D33: =SUMIF(Diario!$C$2:$C$373,A33,Diario!$E$2:$E$373) -> 4708.51 | E33: =COUNTIF(Diario!$C$2:$C$373,A33) -> 12 | F33: =IFERROR(AVERAGEIF(Diario!$C$2:$C$373,A33,Diario!$E$2:$E$373),0) -> 392.37583 | G33: =_xlfn.MAXIFS(Diario!$E$2:$E$373,Diario!$C$2:$C$373,A33) -> 524.67
A34: 999 | B34: =IFERROR(INDEX('Plan contable'!$B$2:$B$16,MATCH(A34,'Plan contable'!$A$2:$A$16,0)),"No existe") -> No existe | C34: {=_xlfn.XLOOKUP(A34,'Plan contable'!$A$2:$A$16,'Plan contable'!$C$2:$C$16,"Sin grupo")} -> Sin grupo | D34: =SUMIF(Diario!$C$2:$C$373,A34,Diario!$E$2:$E$373) -> 0 | E34: =COUNTIF(Diario!$C$2:$C$373,A34) -> 0 | F34: =VLOOKUP(A34,'Plan contable'!$A$2:$C$16,2,FALSE) -> #N/A | G34: =D34/E34 -> #DIV/0!

Sheet Diario
A1: Fecha | B1: Asiento | C1: Cuenta | D1: Concepto | E1: Importe | F1: Grupo | G1: Mes | H1: Trimestre
A2: 45658 | B2: 1 | C2: 600 | D2: Compras de mercaderías enero | E2: 1543.29 | F2: =VLOOKUP(C2,'Plan contable'!$A$2:$C$16,3,FALSE) -> Aprovisionamientos | G2: =MONTH(A2) -> 1 | H2: ="T"&ROUNDUP(G2/3,0) -> T1
A3: 45659 | B3: 2 | C3: 705 | D3: Prestaciones de servicios enero | E3: 915.29 | F3: =VLOOKUP(C3,'Plan contable'!$A$2:$C$16,3,FALSE) -> Importe neto de la cifra de negocios | G3: =MONTH(A3) -> 1 | H3: ="T"&ROUNDUP(G3/3,0) -> T1
A4: 45659 | B4: 3 | C4: 705 | D4: Prestaciones de servicios enero | E4: 1250.29 | F4: =VLOOKUP(C4,'Plan contable'!$A$2:$C$16,3,FALSE) -> Importe neto de la cifra de negocios | G4: =MONTH(A4) -> 1 | H4: ="T"&ROUNDUP(G4/3,0) -> T1
A5: 45660 | B5: 4 | C5: 700 | D5: Ventas de mercaderías enero | E5: 2156.6 | F5: =VLOOKUP(C5,'Plan contable'!$A$2:$C$16,3,FALSE) -> Importe neto de la cifra de negocios | G5: =MONTH(A5) -> 1 | H5: ="T"&ROUNDUP(G5/3,0) -> T1
A6: 45662 | B6: 5 | C6: 700 | D6: Ventas de mercaderías enero | E6: 2187.41 | F6: =VLOOKUP(C6,'Plan contable'!$A$2:$C$16,3,FALSE) -> Importe neto de la cifra de negocios | G6: =MONTH(A6) -> 1 | H6: ="T"&ROUNDUP(G6/3,0) -> T1
A7: 45663 | B7: 6 | C7: 600 | D7: Compras de mercaderías enero | E7: 1959.69 | F7: =VLOOKUP(C7,'Plan contable'!$A$2:$C$16,3,FALSE) -> Aprovisionamientos | G7: =MONTH(A7) -> 1 | H7: ="T"&ROUNDUP(G7/3,0) -> T1
A8: 45663 | B8: 7 | C8: 681 | D8: Amortización del inmovilizado material enero | E8: 1250 | F8: =VLOOKUP(C8,'Plan contable'!$A$2:$C$16,3,FALSE) -> Amortización del inmovilizado | G8: =MONTH(A8) -> 1 | H8: ="T"&ROUNDUP(G8/3,0) -> T1
A9: 45663 | B9: 8 | C9: 700 | D9: Ventas de mercaderías enero | E9: 3488.87 | F9: =VLOOKUP(C9,'Plan contable'!$A$2:$C$16,3,FALSE) -> Importe neto de la cifra de negocios | G9: =MONTH(A9) -> 1 | H9: ="T"&ROUNDUP(G9/3,0) -> T1
A10: 45666 | B10: 9 | C10: 623 | D10: Servicios de profesionales independientes enero | E10: 538.83 | F10: =VLOOKUP(C10,'Plan contable'!$A$2:$C$16,3,FALSE) -> Otros gastos de explotación | G10: =MONTH(A10) -> 1 | H10: ="T"&ROUNDUP(G10/3,0) -> T1
A11: 45666 | B11: 10 | C11: 640 | D11: Sueldos y salarios enero | E11: 14500 | F11: =VLOOKUP(C11,'Plan contable'!$A$2:$C$16,3,FALSE) -> Gastos de personal | G11: =MONTH(A11) -> 1 | H11: ="T"&ROUNDUP(G11/3,0) -> T1
A12: 45667 | B12: 11 | C12: 600 | D12: Compras de mercaderías enero | E12: 1274.43 | F12: =VLOOKUP(C12,'Plan contable'!$A$2:$C$16,3,FALSE) -> Aprovisionamientos | G12: =MONTH(A12) -> 1 | H12: ="T"&ROUNDUP(G12/3,0) -> T1
A13: 45668 | B13: 12 | C13: 607 | D13: Trabajos realizados por otras empresas enero | E13: 842.94 | F13: =VLOOKUP(C13,'Plan contable'!$A$2:$C$16,3,FALSE) -> Aprovisionamientos | G13: =MONTH(A13) -> 1 | H13: ="T"&ROUNDUP(G13/3,0) -> T1
... A373: 46019 | B373: 372 | C373: 629 | D373: Otros servicios diciembre | E373: 90.4 | F373: =VLOOKUP(C373,'Plan contable'!$A$2:$C$16,3,FALSE) -> Otros gastos de explotación | G373: =MONTH(A373) -> 12 | H373: ="T"&ROUNDUP(G373/3,0) -> T4

Sheet Plan contable
A1: Código | B1: Cuenta | C1: Grupo
A2: 700 | B2: Ventas de mercaderías | C2: Importe neto de la cifra de negocios
A3: 705 | B3: Prestaciones de servicios | C3: Importe neto de la cifra de negocios
A4: 600 | B4: Compras de mercaderías | C4: Aprovisionamientos
A5: 607 | B5: Trabajos realizados por otras empresas | C5: Aprovisionamientos
A6: 640 | B6: Sueldos y salarios | C6: Gastos de personal
A7: 642 | B7: Seguridad Social a cargo de la empresa | C7: Gastos de personal
A8: 621 | B8: Arrendamientos y cánones | C8: Otros gastos de explotación
A9: 622 | B9: Reparaciones y conservación | C9: Otros gastos de explotación
A10: 623 | B10: Servicios de profesionales independientes | C10: Otros gastos de explotación
A11: 625 | B11: Primas de seguros | C11: Otros gastos de explotación
A12: 627 | B12: Publicidad, propaganda y relaciones públicas | C12: Otros gastos de explotación
A13: 628 | B13: Suministros | C13: Otros gastos de explotación
... A16: 662 | B16: Intereses de deudas | C16: Gastos financieros

Sheet Préstamo
A1: Préstamo hipotecario
A3: Capital | B3: 150000
A4: Interés anual | B4: 0.045
A5: Años | B5: 10
A6: Fecha de inicio | B6: 45672
A7: Cuota mensual | B7: =PMT(B4/12,B5*12,-B3) -> 1554.5761
A8: Total intereses | B8: =B7*B5*12-B3 -> 36549.136
A9: Fecha fin | B9: =EOMONTH(B6,B5*12-1) -> 49309 | C9: =B9 -> 49309
A11: Nº | B11: Fecha | C11: Cuota | D11: Intereses | E11: Amortización | F11: Capital pendiente
A12: 1 | B12: =EOMONTH($B$6,A12-1) -> 45688 | C12: =$B$7 -> 1554.5761 | D12: =$B$3*$B$4/12 -> 562.5 | E12: =C12-D12 -> 992.07613 | F12: =$B$3-E12 -> 149007.92
A13: 2 | B13: =EOMONTH($B$6,A13-1) -> 45716 | C13: =$B$7 -> 1554.5761 | D13: =F12*$B$4/12 -> 558.77971 | E13: =C13-D13 -> 995.79642 | F13: =F12-E13 -> 148012.13
A14: 3 | B14: =EOMONTH($B$6,A14-1) -> 45747 | C14: =$B$7 -> 1554.5761 | D14: =F13*$B$4/12 -> 555.04548 | E14: =C14-D14 -> 999.53065 | F14: =F13-E14 -> 147012.6
A15: 4 | B15: =EOMONTH($B$6,A15-1) -> 45777 | C15: =$B$7 -> 1554.5761 | D15: =F14*$B$4/12 -> 551.29724 | E15: =C15-D15 -> 1003.2789 | F15: =F14-E15 -> 146009.32
A16: 5 | B16: =EOMONTH($B$6,A16-1) -> 45808 | C16: =$B$7 -> 1554.5761 | D16: =F15*$B$4/12 -> 547.53494 | E16: =C16-D16 -> 1007.0412 | F16: =F15-E16 -> 145002.28
A17: 6 | B17: =EOMONTH($B$6,A17-1) -> 45838 | C17: =$B$7 -> 1554.5761 | D17: =F16*$B$4/12 -> 543.75854 | E17: =C17-D17 -> 1010.8176 | F17: =F16-E17 -> 143991.46
A18: 7 | B18: =EOMONTH($B$6,A18-1) -> 45869 | C18: =$B$7 -> 1554.5761 | D18: =F17*$B$4/12 -> 539.96797 | E18: =C18-D18 -> 1014.6082 | F18: =F17-E18 -> 142976.85
A19: 8 | B19: =EOMONTH($B$6,A19-1) -> 45900 | C19: =$B$7 -> 1554.5761 | D19: =F18*$B$4/12 -> 536.16319 | E19: =C19-D19 -> 1018.4129 | F19: =F18-E19 -> 141958.44
A20: 9 | B20: =EOMONTH($B$6,A20-1) -> 45930 | C20: =$B$7 -> 1554.5761 | D20: =F19*$B$4/12 -> 532.34414 | E20: =C20-D20 -> 1022.232 | F20: =F19-E20 -> 140936.21
A21: 10 | B21: =EOMONTH($B$6,A21-1) -> 45961 | C21: =$B$7 -> 1554.5761 | D21: =F20*$B$4/12 -> 528.51077 | E21: =C21-D21 -> 1026.0654 | F21: =F20-E21 -> 139910.14
A22: 11 | B22: =EOMONTH($B$6,A22-1) -> 45991 | C22: =$B$7 -> 1554.5761 | D22: =F21*$B$4/12 -> 524.66303 | E22: =C22-D22 -> 1029.9131 | F22: =F21-E22 -> 138880.23
A23: 12 | B23: =EOMONTH($B$6,A23-1) -> 46022 | C23: =$B$7 -> 1554.5761 | D23: =F22*$B$4/12 -> 520.80085 | E23: =C23-D23 -> 1033.7753 | F23: =F22-E23 -> 137846.45
A24: 13 | B24: =EOMONTH($B$6,A24-1) -> 46053 | C24: =$B$7 -> 1554.5761 | D24: =F23*$B$4/12 -> 516.9242 | E24: =C24-D24 -> 1037.6519 | F24: =F23-E24 -> 136808.8
... A35: 24 | B35: =EOMONTH($B$6,A35-1) -> 46387 | C35: =$B$7 -> 1554.5761 | D35: =F34*$B$4/12 -> 473.3094 | E35: =C35-D35 -> 1081.2667 | F35: =F34-E35 -> 125134.57
A36: Totales 24 meses | C36: =SUM(C12:C35) -> 37309.827 | D36: =SUM(D12:D35) -> 12444.4 | E36: =SUM(E12:E35) -> 24865.427

Sheet Inversión
A1: Análisis de inversión
A3: Tasa de descuento | B3: 0.08
A5: Año | B5: Flujo de caja
A6: 0 | B6: -50000
A7: 1 | B7: 12000
A8: 2 | B8: 15000
A9: 3 | B9: 18000
A10: 4 | B10: 20000
A11: 5 | B11: 22000
A13: VAN | B13: =NPV(B3,B7:B11)+B6 -> 17933.601
A14: TIR | B14: =IRR(B6:B11) -> 0.19442495
A15: Ahorro a 5 años (300 €/mes al 3 %) | B15: =FV(0.03/12,60,-300,0,0) -> 19394.014
A16: Plazo de recuperación (años) | B16: =ROUND(3+(-(B6+B7+B8+B9))/B10,2) -> 3.25
