Workbook

Sheet Presupuesto 2025
A1: Presupuesto familiar 2025
A2: Importes en euros. Real según la hoja Movimientos.
A3: Categoría | B3: Ene | C3: Feb | D3: Mar | E3: Abr | F3: May | G3: Jun | H3: Jul | I3: Ago | J3: Sep | K3: Oct | L3: Nov | M3: Dic | N3: Total | O3: Media | P3: % s/ total | Q3: Total (SUMIF) | R3: Presupuesto | S3: Desviación | T3: % ejecutado
A4: INGRESOS
A5: Nómina | B5: =SUMIFS(Movimientos!$E$2:$E$312,Movimientos!$C$2:$C$312,$A5,Movimientos!$F$2:$F$312,1) -> 2450 | C5: =SUMIFS(Movimientos!$E$2:$E$312,Movimientos!$C$2:$C$312,$A5,Movimientos!$F$2:$F$312,2) -> 2450 | D5: =SUMIFS(Movimientos!$E$2:$E$312,Movimientos!$C$2:$C$312,$A5,Movimientos!$F$2:$F$312,3) -> 2450 | E5: =SUMIFS(Movimientos!$E$2:$E$312,Movimientos!$C$2:$C$312,$A5,Movimientos!$F$2:$F$312,4) -> 2450 | F5: =SUMIFS(Movimientos!$E$2:$E$312,Movimientos!$C$2:$C$312,$A5,Movimientos!$F$2:$F$312,5) -> 2450 | G5: =SUMIFS(Movimientos!$E$2:$E$312,Movimientos!$C$2:$C$312,$A5,Movimientos!$F$2:$F$312,6) -> 4900 | H5: =SUMIFS(Movimientos!$E$2:$E$312,Movimientos!$C$2:$C$312,$A5,Movimientos!$F$2:$F$312,7) -> 2450 | I5: =SUMIFS(Movimientos!$E$2:$E$312,Movimientos!$C$2:$C$312,$A5,Movimientos!$F$2:$F$312,8) -> 2450 | J5: =SUMIFS(Movimientos!$E$2:$E$312,Movimientos!$C$2:$C$312,$A5,Movimientos!$F$2:$F$312,9) -> 2450 | K5: =SUMIFS(Movimientos!$E$2:$E$312,Movimientos!$C$2:$C$312,$A5,Movimientos!$F$2:$F$312,10) -> 2450 | L5: =SUMIFS(Movimientos!$E$2:$E$312,Movimientos!$C$2:$C$312,$A5,Movimientos!$F$2:$F$312,11) -> 2450 | M5: =SUMIFS(Movimientos!$E$2:$E$312,Movimientos!$C$2:$C$312,$A5,Movimientos!$F$2:$F$312,12) -> 4900 | N5: =SUM(B5:M5) -> 34300 | O5: =AVERAGE(B5:M5) -> 2858.3333 | P5: =N5/N$8 -> 0.54263935 | Q5: =SUMIF(Movimientos!$C$2:$C$312,$A5,Movimientos!$E$2:$E$312) -> 34300 | R5: =VLOOKUP($A5,Categorías!$A$2:$C$19,3,FALSE)*12 -> 29400 | S5: =N5-R5 -> 4900 | T5: =IF(R5=0,0,N5/R5) -> 1.1666667
A6: Nómina pareja | B6: =SUMIFS(Movimientos!$E$2:$E$312,Movimientos!$C$2:$C$312,$A6,Movimientos!$F$2:$F$312,1) -> 1980 | C6: =SUMIFS(Movimientos!$E$2:$E$312,Movimientos!$C$2:$C$312,$A6,Movimientos!$F$2:$F$312,2) -> 1980 | D6: =SUMIFS(Movimientos!$E$2:$E$312,Movimientos!$C$2:$C$312,$A6,Movimientos!$F$2:$F$312,3) -> 1980 | E6: =SUMIFS(Movimientos!$E$2:$E$312,Movimientos!$C$2:$C$312,$A6,Movimientos!$F$2:$F$312,4) -> 1980 | F6: =SUMIFS(Movimientos!$E$2:$E$312,Movimientos!$C$2:$C$312,$A6,Movimientos!$F$2:$F$312,5) -> 1980 | G6: =SUMIFS(Movimientos!$E$2:$E$312,Movimientos!$C$2:$C$312,$A6,Movimientos!$F$2:$F$312,6) -> 1980 | H6: =SUMIFS(Movimientos!$E$2:$E$312,Movimientos!$C$2:$C$312,$A6,Movimientos!$F$2:$F$312,7) -> 3960 | I6: =SUMIFS(Movimientos!$E$2:$E$312,Movimientos!$C$2:$C$312,$A6,Movimientos!$F$2:$F$312,8) -> 1980 | J6: =SUMIFS(Movimientos!$E$2:$E$312,Movimientos!$C$2:$C$312,$A6,Movimientos!$F$2:$F$312,9) -> 1980 | K6: =SUMIFS(Movimientos!$E$2:$E$312,Movimientos!$C$2:$C$312,$A6,Movimientos!$F$2:$F$312,10) -> 1980 | L6: =SUMIFS(Movimientos!$E$2:$E$312,Movimientos!$C$2:$C$312,$A6,Movimientos!$F$2:$F$312,11) -> 1980 | M6: =SUMIFS(Movimientos!$E$2:$E$312,Movimientos!$C$2:$C$312,$A6,Movimientos!$F$2:$F$312,12) -> 3960 | N6: =SUM(B6:M6) -> 27720 | O6: =AVERAGE(B6:M6) -> 2310 | P6: =N6/N$8 -> 0.43854119 | Q6: =SUMIF(Movimientos!$C$2:$C$312,$A6,Movimientos!$E$2:$E$312) -> 27720 | R6: =VLOOKUP($A6,Categorías!$A$2:$C$19,3,FALSE)*12 -> 23760 | S6: =N6-R6 -> 3960 | T6: =IF(R6=0,0,N6/R6) -> 1.1666667
A7: Extras | B7: =SUMIFS(Movimientos!$E$2:$E$312,Movimientos!$C$2:$C$312,$A7,Movimientos!$F$2:$F$312,1) -> 193.62 | C7: =SUMIFS(Movimientos!$E$2:$E$312,Movimientos!$C$2:$C$312,$A7,Movimientos!$F$2:$F$312,2) -> 278.96 | D7: =SUMIFS(Movimientos!$E$2:$E$312,Movimientos!$C$2:$C$312,$A7,Movimientos!$F$2:$F$312,3) -> 171.3 | E7: =SUMIFS(Movimientos!$E$2:$E$312,Movimientos!$C$2:$C$312,$A7,Movimientos!$F$2:$F$312,4) -> 0 | F7: =SUMIFS(Movimientos!$E$2:$E$312,Movimientos!$C$2:$C$312,$A7,Movimientos!$F$2:$F$312,5) -> 0 | G7: =SUMIFS(Movimientos!$E$2:$E$312,Movimientos!$C$2:$C$312,$A7,Movimientos!$F$2:$F$312,6) -> 0 | H7: =SUMIFS(Movimientos!$E$2:$E$312,Movimientos!$C$2:$C$312,$A7,Movimientos!$F$2:$F$312,7) -> 0 | I7: =SUMIFS(Movimientos!$E$2:$E$312,Movimientos!$C$2:$C$312,$A7,Movimientos!$F$2:$F$312,8) -> 0 | J7: =SUMIFS(Movimientos!$E$2:$E$312,Movimientos!$C$2:$C$312,$A7,Movimientos!$F$2:$F$312,9) -> 0 | K7: =SUMIFS(Movimientos!$E$2:$E$312,Movimientos!$C$2:$C$312,$A7,Movimientos!$F$2:$F$312,10) -> 165.87 | L7: =SUMIFS(Movimientos!$E$2:$E$312,Movimientos!$C$2:$C$312,$A7,Movimientos!$F$2:$F$312,11) -> 0 | M7: =SUMIFS(Movimientos!$E$2:$E$312,Movimientos!$C$2:$C$312,$A7,Movimientos!$F$2:$F$312,12) -> 379.82 | N7: =SUM(B7:M7) -> 1189.57 | O7: =AVERAGE(B7:M7) -> 99.130833 | P7: =N7/N$8 -> 0.01881946 | Q7: =SUMIF(Movimientos!$C$2:$C$312,$A7,Movimientos!$E$2:$E$312) -> 1189.57 | R7: =VLOOKUP($A7,Categorías!$A$2:$C$19,3,FALSE)*12 -> 1800 | S7: =N7-R7 -> -610.43 | T7: =IF(R7=0,0,N7/R7) -> 0.66087222
A8: Total ingresos | B8: =SUM(B5:B7) -> 4623.62 | C8: =SUM(C5:C7) -> 4708.96 | D8: =SUM(D5:D7) -> 4601.3 | E8: =SUM(E5:E7) -> 4430 | F8: =SUM(F5:F7) -> 4430 | G8: =SUM(G5:G7) -> 6880 | H8: =SUM(H5:H7) -> 6410 | I8: =SUM(I5:I7) -> 4430 | ... N8: =SUM(N5:N7) -> 63209.57 | O8: =AVERAGE(B8:M8) -> 5267.4642 | P8: =SUM(P5:P7) -> 1 | Q8: =SUM(Q5:Q7) -> 63209.57 | R8: =SUM(R5:R7) -> 54960 | S8: =N8-R8 -> 8249.57 | T8: =IF(R8=0,0,N8/R8) -> 1.1501013
A10: GASTOS
A11: Hipoteca | B11: =SUMIFS(Movimientos!$E$2:$E$312,Movimientos!$C$2:$C$312,$A11,Movimientos!$F$2:$F$312,1) -> 780 | C11: =SUMIFS(Movimientos!$E$2:$E$312,Movimientos!$C$2:$C$312,$A11,Movimientos!$F$2:$F$312,2) -> 780 | D11: =SUMIFS(Movimientos!$E$2:$E$312,Movimientos!$C$2:$C$312,$A11,Movimientos!$F$2:$F$312,3) -> 780 | E11: =SUMIFS(Movimientos!$E$2:$E$312,Movimientos!$C$2:$C$312,$A11,Movimientos!$F$2:$F$312,4) -> 780 | F11: =SUMIFS(Movimientos!$E$2:$E$312,Movimientos!$C$2:$C$312,$A11,Movimientos!$F$2:$F$312,5) -> 780 | G11: =SUMIFS(Movimientos!$E$2:$E$312,Movimientos!$C$2:$C$312,$A11,Movimientos!$F$2:$F$312,6) -> 780 | H11: =SUMIFS(Movimientos!$E$2:$E$312,Movimientos!$C$2:$C$312,$A11,Movimientos!$F$2:$F$312,7) -> 780 | I11: =SUMIFS(Movimientos!$E$2:$E$312,Movimientos!$C$2:$C$312,$A11,Movimientos!$F$2:$F$312,8) -> 780 | J11: =SUMIFS(Movimientos!$E$2:$E$312,Movimientos!$C$2:$C$312,$A11,Movimientos!$F$2:$F$312,9) -> 780 | K11: =SUMIFS(Movimientos!$E$2:$E$312,Movimientos!$C$2:$C$312,$A11,Movimientos!$F$2:$F$312,10) -> 780 | L11: =SUMIFS(Movimientos!$E$2:$E$312,Movimientos!$C$2:$C$312,$A11,Movimientos!$F$2:$F$312,11) -> 780 | M11: =SUMIFS(Movimientos!$E$2:$E$312,Movimientos!$C$2:$C$312,$A11,Movimientos!$F$2:$F$312,12) -> 780 | N11: =SUM(B11:M11) -> 9360 | O11: =AVERAGE(B11:M11) -> 780 | P11: =N11/N$26 -> 0.35648343 | Q11: =SUMIF(Movimientos!$C$2:$C$312,$A11,Movimientos!$E$2:$E$312) -> 9360 | R11: =VLOOKUP($A11,Categorías!$A$2:$C$19,3,FALSE)*12 -> 9360 | S11: =N11-R11 -> 0 | T11: =IF(R11=0,0,N11/R11) -> 1
A12: Comunidad | B12: =SUMIFS(Movimientos!$E$2:$E$312,Movimientos!$C$2:$C$312,$A12,Movimientos!$F$2:$F$312,1) -> 65 | C12: =SUMIFS(Movimientos!$E$2:$E$312,Movimientos!$C$2:$C$312,$A12,Movimientos!$F$2:$F$312,2) -> 65 | D12: =SUMIFS(Movimientos!$E$2:$E$312,Movimientos!$C$2:$C$312,$A12,Movimientos!$F$2:$F$312,3) -> 65 | E12: =SUMIFS(Movimientos!$E$2:$E$312,Movimientos!$C$2:$C$312,$A12,Movimientos!$F$2:$F$312,4) -> 65 | F12: =SUMIFS(Movimientos!$E$2:$E$312,Movimientos!$C$2:$C$312,$A12,Movimientos!$F$2:$F$312,5) -> 65 | G12: =SUMIFS(Movimientos!$E$2:$E$312,Movimientos!$C$2:$C$312,$A12,Movimientos!$F$2:$F$312,6) -> 65 | H12: =SUMIFS(Movimientos!$E$2:$E$312,Movimientos!$C$2:$C$312,$A12,Movimientos!$F$2:$F$312,7) -> 65 | I12: =SUMIFS(Movimientos!$E$2:$E$312,Movimientos!$C$2:$C$312,$A12,Movimientos!$F$2:$F$312,8) -> 65 | J12: =SUMIFS(Movimientos!$E$2:$E$312,Movimientos!$C$2:$C$312,$A12,Movimientos!$F$2:$F$312,9) -> 65 | K12: =SUMIFS(Movimientos!$E$2:$E$312,Movimientos!$C$2:$C$312,$A12,Movimientos!$F$2:$F$312,10) -> 65 | L12: =SUMIFS(Movimientos!$E$2:$E$312,Movimientos!$C$2:$C$312,$A12,Movimientos!$F$2:$F$312,11) -> 65 | M12: =SUMIFS(Movimientos!$E$2:$E$312,Movimientos!$C$2:$C$312,$A12,Movimientos!$F$2:$F$312,12) -> 65 | N12: =SUM(B12:M12) -> 780 | O12: =AVERAGE(B12:M12) -> 65 | P12: =N12/N$26 -> 0.029706952 | Q12: =SUMIF(Movimientos!$C$2:$C$312,$A12,Movimientos!$E$2:$E$312) -> 780 | R12: =VLOOKUP($A12,Categorías!$A$2:$C$19,3,FALSE)*12 -> 780 | S12: =N12-R12 -> 0 | T12: =IF(R12=0,0,N12/R12) -> 1
A13: Luz | B13: =SUMIFS(Movimientos!$E$2:$E$312,Movimientos!$C$2:$C$312,$A13,Movimientos!$F$2:$F$312,1) -> 60.15 | C13: =SUMIFS(Movimientos!$E$2:$E$312,Movimientos!$C$2:$C$312,$A13,Movimientos!$F$2:$F$312,2) -> 73.44 | D13: =SUMIFS(Movimientos!$E$2:$E$312,Movimientos!$C$2:$C$312,$A13,Movimientos!$F$2:$F$312,3) -> 53.77 | E13: =SUMIFS(Movimientos!$E$2:$E$312,Movimientos!$C$2:$C$312,$A13,Movimientos!$F$2:$F$312,4) -> 71.18 | F13: =SUMIFS(Movimientos!$E$2:$E$312,Movimientos!$C$2:$C$312,$A13,Movimientos!$F$2:$F$312,5) -> 86.48 | G13: =SUMIFS(Movimientos!$E$2:$E$312,Movimientos!$C$2:$C$312,$A13,Movimientos!$F$2:$F$312,6) -> 99 | H13: =SUMIFS(Movimientos!$E$2:$E$312,Movimientos!$C$2:$C$312,$A13,Movimientos!$F$2:$F$312,7) -> 76.22 | I13: =SUMIFS(Movimientos!$E$2:$E$312,Movimientos!$C$2:$C$312,$A13,Movimientos!$F$2:$F$312,8) -> 77.37 | J13: =SUMIFS(Movimientos!$E$2:$E$312,Movimientos!$C$2:$C$312,$A13,Movimientos!$F$2:$F$312,9) -> 56.48 | K13: =SUMIFS(Movimientos!$E$2:$E$312,Movimientos!$C$2:$C$312,$A13,Movimientos!$F$2:$F$312,10) -> 86.71 | L13: =SUMIFS(Movimientos!$E$2:$E$312,Movimientos!$C$2:$C$312,$A13,Movimientos!$F$2:$F$312,11) -> 55.66 | M13: =SUMIFS(Movimientos!$E$2:$E$312,Movimientos!$C$2:$C$312,$A13,Movimientos!$F$2:$F$312,12) -> 58.02 | N13: =SUM(B13:M13) -> 854.48 | O13: =AVERAGE(B13:M13) -> 71.206667 | P13: =N13/N$26 -> 0.032543585 | Q13: =SUMIF(Movimientos!$C$2:$C$312,$A13,Movimientos!$E$2:$E$312) -> 854.48 | R13: =VLOOKUP($A13,Categorías!$A$2:$C$19,3,FALSE)*12 -> 864 | S13: =N13-R13 -> -9.52 | T13: =IF(R13=0,0,N13/R13) -> 0.98898148
A14: Agua | B14: =SUMIFS(Movimientos!$E$2:$E$312,Movimientos!$C$2:$C$312,$A14,Movimientos!$F$2:$F$312,1) -> 60.51 | C14: =SUMIFS(Movimientos!$E$2:$E$312,Movimientos!$C$2:$C$312,$A14,Movimientos!$F$2:$F$312,2) -> 0 | D14: =SUMIFS(Movimientos!$E$2:$E$312,Movimientos!$C$2:$C$312,$A14,Movimientos!$F$2:$F$312,3) -> 54.32 | E14: =SUMIFS(Movimientos!$E$2:$E$312,Movimientos!$C$2:$C$312,$A14,Movimientos!$F$2:$F$312,4) -> 0 | F14: =SUMIFS(Movimientos!$E$2:$E$312,Movimientos!$C$2:$C$312,$A14,Movimientos!$F$2:$F$312,5) -> 51.47 | G14: =SUMIFS(Movimientos!$E$2:$E$312,Movimientos!$C$2:$C$312,$A14,Movimientos!$F$2:$F$312,6) -> 0 | H14: =SUMIFS(Movimientos!$E$2:$E$312,Movimientos!$C$2:$C$312,$A14,Movimientos!$F$2:$F$312,7) -> 53.41 | I14: =SUMIFS(Movimientos!$E$2:$E$312,Movimientos!$C$2:$C$312,$A14,Movimientos!$F$2:$F$312,8) -> 0 | J14: =SUMIFS(Movimientos!$E$2:$E$312,Movimientos!$C$2:$C$312,$A14,Movimientos!$F$2:$F$312,9) -> 40.47 | K14: =SUMIFS(Movimientos!$E$2:$E$312,Movimientos!$C$2:$C$312,$A14,Movimientos!$F$2:$F$312,10) -> 0 | L14: =SUMIFS(Movimientos!$E$2:$E$312,Movimientos!$C$2:$C$312,$A14,Movimientos!$F$2:$F$312,11) -> 49.07 | M14: =SUMIFS(Movimientos!$E$2:$E$312,Movimientos!$C$2:$C$312,$A14,Movimientos!$F$2:$F$312,12) -> 0 | N14: =SUM(B14:M14) -> 309.25 | O14: =AVERAGE(B14:M14) -> 25.770833 | P14: =N14/N$26 -> 0.011778045 | Q14: =SUMIF(Movimientos!$C$2:$C$312,$A14,Movimientos!$E$2:$E$312) -> 309.25 | R14: =VLOOKUP($A14,Categorías!$A$2:$C$19,3,FALSE)*12 -> 336 | S14: =N14-R14 -> -26.75 | T14: =IF(R14=0,0,N14/R14) -> 0.9203869
A15: Gas | B15: =SUMIFS(Movimientos!$E$2:$E$312,Movimientos!$C$2:$C$312,$A15,Movimientos!$F$2:$F$312,1) -> 93.79 | C15: =SUMIFS(Movimientos!$E$2:$E$312,Movimientos!$C$2:$C$312,$A15,Movimientos!$F$2:$F$312,2) -> 73.65 | D15: =SUMIFS(Movimientos!$E$2:$E$312,Movimientos!$C$2:$C$312,$A15,Movimientos!$F$2:$F$312,3) -> 82.15 | E15: =SUMIFS(Movimientos!$E$2:$E$312,Movimientos!$C$2:$C$312,$A15,Movimientos!$F$2:$F$312,4) -> 33.15 | F15: =SUMIFS(Movimientos!$E$2:$E$312,Movimientos!$C$2:$C$312,$A15,Movimientos!$F$2:$F$312,5) -> 21.91 | G15: =SUMIFS(Movimientos!$E$2:$E$312,Movimientos!$C$2:$C$312,$A15,Movimientos!$F$2:$F$312,6) -> 34.73 | H15: =SUMIFS(Movimientos!$E$2:$E$312,Movimientos!$C$2:$C$312,$A15,Movimientos!$F$2:$F$312,7) -> 31.06 | I15: =SUMIFS(Movimientos!$E$2:$E$312,Movimientos!$C$2:$C$312,$A15,Movimientos!$F$2:$F$312,8) -> 33.65 | J15: =SUMIFS(Movimientos!$E$2:$E$312,Movimientos!$C$2:$C$312,$A15,Movimientos!$F$2:$F$312,9) -> 24.59 | K15: =SUMIFS(Movimientos!$E$2:$E$312,Movimientos!$C$2:$C$312,$A15,Movimientos!$F$2:$F$312,10) -> 19.61 | L15: =SUMIFS(Movimientos!$E$2:$E$312,Movimientos!$C$2:$C$312,$A15,Movimientos!$F$2:$F$312,11) -> 98.75 | M15: =SUMIFS(Movimientos!$E$2:$E$312,Movimientos!$C$2:$C$312,$A15,Movimientos!$F$2:$F$312,12) -> 107.73 | N15: =SUM(B15:M15) -> 654.77 | O15: =AVERAGE(B15:M15) -> 54.564167 | P15: =N15/N$26 -> 0.024937463 | Q15: =SUMIF(Movimientos!$C$2:$C$312,$A15,Movimientos!$E$2:$E$312) -> 654.77 | R15: =VLOOKUP($A15,Categorías!$A$2:$C$19,3,FALSE)*12 -> 540 | S15: =N15-R15 -> 114.77 | T15: =IF(R15=0,0,N15/R15) -> 1.212537
A16: Internet y móvil | B16: =SUMIFS(Movimientos!$E$2:$E$312,Movimientos!$C$2:$C$312,$A16,Movimientos!$F$2:$F$312,1) -> 59.9 | C16: =SUMIFS(Movimientos!$E$2:$E$312,Movimientos!$C$2:$C$312,$A16,Movimientos!$F$2:$F$312,2) -> 59.9 | D16: =SUMIFS(Movimientos!$E$2:$E$312,Movimientos!$C$2:$C$312,$A16,Movimientos!$F$2:$F$312,3) -> 59.9 | E16: =SUMIFS(Movimientos!$E$2:$E$312,Movimientos!$C$2:$C$312,$A16,Movimientos!$F$2:$F$312,4) -> 59.9 | F16: =SUMIFS(Movimientos!$E$2:$E$312,Movimientos!$C$2:$C$312,$A16,Movimientos!$F$2:$F$312,5) -> 59.9 | G16: =SUMIFS(Movimientos!$E$2:$E$312,Movimientos!$C$2:$C$312,$A16,Movimientos!$F$2:$F$312,6) -> 59.9 | H16: =SUMIFS(Movimientos!$E$2:$E$312,Movimientos!$C$2:$C$312,$A16,Movimientos!$F$2:$F$312,7) -> 59.9 | I16: =SUMIFS(Movimientos!$E$2:$E$312,Movimientos!$C$2:$C$312,$A16,Movimientos!$F$2:$F$312,8) -> 59.9 | J16: =SUMIFS(Movimientos!$E$2:$E$312,Movimientos!$C$2:$C$312,$A16,Movimientos!$F$2:$F$312,9) -> 59.9 | K16: =SUMIFS(Movimientos!$E$2:$E$312,Movimientos!$C$2:$C$312,$A16,Movimientos!$F$2:$F$312,10) -> 59.9 | L16: =SUMIFS(Movimientos!$E$2:$E$312,Movimientos!$C$2:$C$312,$A16,Movimientos!$F$2:$F$312,11) -> 59.9 | M16: =SUMIFS(Movimientos!$E$2:$E$312,Movimientos!$C$2:$C$312,$A16,Movimientos!$F$2:$F$312,12) -> 59.9 | N16: =SUM(B16:M16) -> 718.8 | O16: =AVERAGE(B16:M16) -> 59.9 | P16: =N16/N$26 -> 0.027376099 | Q16: =SUMIF(Movimientos!$C$2:$C$312,$A16,Movimientos!$E$2:$E$312) -> 718.8 | R16: =VLOOKUP($A16,Categorías!$A$2:$C$19,3,FALSE)*12 -> 718.8 | S16: =N16-R16 -> 0 | T16: =IF(R16=0,0,N16/R16) -> 1
A17: Supermercado | B17: =SUMIFS(Movimientos!$E$2:$E$312,Movimientos!$C$2:$C$312,$A17,Movimientos!$F$2:$F$312,1) -> 415.06 | C17: =SUMIFS(Movimientos!$E$2:$E$312,Movimientos!$C$2:$C$312,$A17,Movimientos!$F$2:$F$312,2) -> 290.33 | D17: =SUMIFS(Movimientos!$E$2:$E$312,Movimientos!$C$2:$C$312,$A17,Movimientos!$F$2:$F$312,3) -> 559.03 | E17: =SUMIFS(Movimientos!$E$2:$E$312,Movimientos!$C$2:$C$312,$A17,Movimientos!$F$2:$F$312,4) -> 516.1 | F17: =SUMIFS(Movimientos!$E$2:$E$312,Movimientos!$C$2:$C$312,$A17,Movimientos!$F$2:$F$312,5) -> 536.39 | G17: =SUMIFS(Movimientos!$E$2:$E$312,Movimientos!$C$2:$C$312,$A17,Movimientos!$F$2:$F$312,6) -> 345.82 | H17: =SUMIFS(Movimientos!$E$2:$E$312,Movimientos!$C$2:$C$312,$A17,Movimientos!$F$2:$F$312,7) -> 531.82 | I17: =SUMIFS(Movimientos!$E$2:$E$312,Movimientos!$C$2:$C$312,$A17,Movimientos!$F$2:$F$312,8) -> 372.6 | J17: =SUMIFS(Movimientos!$E$2:$E$312,Movimientos!$C$2:$C$312,$A17,Movimientos!$F$2:$F$312,9) -> 432.01 | K17: =SUMIFS(Movimientos!$E$2:$E$312,Movimientos!$C$2:$C$312,$A17,Movimientos!$F$2:$F$312,10) -> 379.44 | L17: =SUMIFS(Movimientos!$E$2:$E$312,Movimientos!$C$2:$C$312,$A17,Movimientos!$F$2:$F$312,11) -> 355.86 | M17: =SUMIFS(Movimientos!$E$2:$E$312,Movimientos!$C$2:$C$312,$A17,Movimientos!$F$2:$F$312,12) -> 537.42 | N17: =SUM(B17:M17) -> 5271.88 | O17: =AVERAGE(B17:M17) -> 439.32333 | P17: =N17/N$26 -> 0.20078396 | Q17: =SUMIF(Movimientos!$C$2:$C$312,$A17,Movimientos!$E$2:$E$312) -> 5271.88 | R17: =VLOOKUP($A17,Categorías!$A$2:$C$19,3,FALSE)*12 -> 6240 | S17: =N17-R17 -> -968.12 | T17: =IF(R17=0,0,N17/R17) -> 0.84485256
A18: Transporte | B18: =SUMIFS(Movimientos!$E$2:$E$312,Movimientos!$C$2:$C$312,$A18,Movimientos!$F$2:$F$312,1) -> 72.15 | C18: =SUMIFS(Movimientos!$E$2:$E$312,Movimientos!$C$2:$C$312,$A18,Movimientos!$F$2:$F$312,2) -> 66.33 | D18: =SUMIFS(Movimientos!$E$2:$E$312,Movimientos!$C$2:$C$312,$A18,Movimientos!$F$2:$F$312,3) -> 156.27 | E18: =SUMIFS(Movimientos!$E$2:$E$312,Movimientos!$C$2:$C$312,$A18,Movimientos!$F$2:$F$312,4) -> 122.95 | F18: =SUMIFS(Movimientos!$E$2:$E$312,Movimientos!$C$2:$C$312,$A18,Movimientos!$F$2:$F$312,5) -> 122.41 | G18: =SUMIFS(Movimientos!$E$2:$E$312,Movimientos!$C$2:$C$312,$A18,Movimientos!$F$2:$F$312,6) -> 63.59 | H18: =SUMIFS(Movimientos!$E$2:$E$312,Movimientos!$C$2:$C$312,$A18,Movimientos!$F$2:$F$312,7) -> 187.92 | I18: =SUMIFS(Movimientos!$E$2:$E$312,Movimientos!$C$2:$C$312,$A18,Movimientos!$F$2:$F$312,8) -> 48.84 | J18: =SUMIFS(Movimientos!$E$2:$E$312,Movimientos!$C$2:$C$312,$A18,Movimientos!$F$2:$F$312,9) -> 124.77 | K18: =SUMIFS(Movimientos!$E$2:$E$312,Movimientos!$C$2:$C$312,$A18,Movimientos!$F$2:$F$312,10) -> 112.98 | L18: =SUMIFS(Movimientos!$E$2:$E$312,Movimientos!$C$2:$C$312,$A18,Movimientos!$F$2:$F$312,11) -> 148.04 | M18: =SUMIFS(Movimientos!$E$2:$E$312,Movimientos!$C$2:$C$312,$A18,Movimientos!$F$2:$F$312,12) -> 62.9 | N18: =SUM(B18:M18) -> 1289.15 | O18: =AVERAGE(B18:M18) -> 107.42917 | P18: =N18/N$26 -> 0.049098356 | Q18: =SUMIF(Movimientos!$C$2:$C$312,$A18,Movimientos!$E$2:$E$312) -> 1289.15 | R18: =VLOOKUP($A18,Categorías!$A$2:$C$19,3,FALSE)*12 -> 1680 | S18: =N18-R18 -> -390.85 | T18: =IF(R18=0,0,N18/R18) -> 0.76735119
A19: Seguros | B19: =SUMIFS(Movimientos!$E$2:$E$312,Movimientos!$C$2:$C$312,$A19,Movimientos!$F$2:$F$312,1) -> 35 | C19: =SUMIFS(Movimientos!$E$2:$E$312,Movimientos!$C$2:$C$312,$A19,Movimientos!$F$2:$F$312,2) -> 35 | D19: =SUMIFS(Movimientos!$E$2:$E$312,Movimientos!$C$2:$C$312,$A19,Movimientos!$F$2:$F$312,3) -> 455 | E19: =SUMIFS(Movimientos!$E$2:$E$312,Movimientos!$C$2:$C$312,$A19,Movimientos!$F$2:$F$312,4) -> 35 | F19: =SUMIFS(Movimientos!$E$2:$E$312,Movimientos!$C$2:$C$312,$A19,Movimientos!$F$2:$F$312,5) -> 35 | G19: =SUMIFS(Movimientos!$E$2:$E$312,Movimientos!$C$2:$C$312,$A19,Movimientos!$F$2:$F$312,6) -> 35 | H19: =SUMIFS(Movimientos!$E$2:$E$312,Movimientos!$C$2:$C$312,$A19,Movimientos!$F$2:$F$312,7) -> 35 | I19: =SUMIFS(Movimientos!$E$2:$E$312,Movimientos!$C$2:$C$312,$A19,Movimientos!$F$2:$F$312,8) -> 35 | J19: =SUMIFS(Movimientos!$E$2:$E$312,Movimientos!$C$2:$C$312,$A19,Movimientos!$F$2:$F$312,9) -> 35 | K19: =SUMIFS(Movimientos!$E$2:$E$312,Movimientos!$C$2:$C$312,$A19,Movimientos!$F$2:$F$312,10) -> 35 | L19: =SUMIFS(Movimientos!$E$2:$E$312,Movimientos!$C$2:$C$312,$A19,Movimientos!$F$2:$F$312,11) -> 35 | M19: =SUMIFS(Movimientos!$E$2:$E$312,Movimientos!$C$2:$C$312,$A19,Movimientos!$F$2:$F$312,12) -> 35 | N19: =SUM(B19:M19) -> 840 | O19: =AVERAGE(B19:M19) -> 70 | P19: =N19/N$26 -> 0.031992103 | Q19: =SUMIF(Movimientos!$C$2:$C$312,$A19,Movimientos!$E$2:$E$312) -> 840 | R19: =VLOOKUP($A19,Categorías!$A$2:$C$19,3,FALSE)*12 -> 1020 | S19: =N19-R19 -> -180 | T19: =IF(R19=0,0,N19/R19) -> 0.82352941
A20: Ocio | B20: =SUMIFS(Movimientos!$E$2:$E$312,Movimientos!$C$2:$C$312,$A20,Movimientos!$F$2:$F$312,1) -> 132.12 | C20: =SUMIFS(Movimientos!$E$2:$E$312,Movimientos!$C$2:$C$312,$A20,Movimientos!$F$2:$F$312,2) -> 178.57 | D20: =SUMIFS(Movimientos!$E$2:$E$312,Movimientos!$C$2:$C$312,$A20,Movimientos!$F$2:$F$312,3) -> 174.48 | E20: =SUMIFS(Movimientos!$E$2:$E$312,Movimientos!$C$2:$C$312,$A20,Movimientos!$F$2:$F$312,4) -> 127.97 | F20: =SUMIFS(Movimientos!$E$2:$E$312,Movimientos!$C$2:$C$312,$A20,Movimientos!$F$2:$F$312,5) -> 115.56 | G20: =SUMIFS(Movimientos!$E$2:$E$312,Movimientos!$C$2:$C$312,$A20,Movimientos!$F$2:$F$312,6) -> 86.68 | H20: =SUMIFS(Movimientos!$E$2:$E$312,Movimientos!$C$2:$C$312,$A20,Movimientos!$F$2:$F$312,7) -> 188.08 | I20: =SUMIFS(Movimientos!$E$2:$E$312,Movimientos!$C$2:$C$312,$A20,Movimientos!$F$2:$F$312,8) -> 174.99 | J20: =SUMIFS(Movimientos!$E$2:$E$312,Movimientos!$C$2:$C$312,$A20,Movimientos!$F$2:$F$312,9) -> 115.25 | K20: =SUMIFS(Movimientos!$E$2:$E$312,Movimientos!$C$2:$C$312,$A20,Movimientos!$F$2:$F$312,10) -> 184.53 | L20: =SUMIFS(Movimientos!$E$2:$E$312,Movimientos!$C$2:$C$312,$A20,Movimientos!$F$2:$F$312,11) -> 44.03 | M20: =SUMIFS(Movimientos!$E$2:$E$312,Movimientos!$C$2:$C$312,$A20,Movimientos!$F$2:$F$312,12) -> 49.82 | N20: =SUM(B20:M20) -> 1572.08 | O20: =AVERAGE(B20:M20) -> 131.00667 | P20: =N20/N$26 -> 0.059873982 | Q20: =SUMIF(Movimientos!$C$2:$C$312,$A20,Movimientos!$E$2:$E$312) -> 1572.08 | R20: =VLOOKUP($A20,Categorías!$A$2:$C$19,3,FALSE)*12 -> 2160 | S20: =N20-R20 -> -587.92 | T20: =IF(R20=0,0,N20/R20) -> 0.72781481
A21: Restaurantes | B21: =SUMIFS(Movimientos!$E$2:$E$312,Movimientos!$C$2:$C$312,$A21,Movimientos!$F$2:$F$312,1) -> 203.44 | C21: =SUMIFS(Movimientos!$E$2:$E$312,Movimientos!$C$2:$C$312,$A21,Movimientos!$F$2:$F$312,2) -> 41.66 | D21: =SUMIFS(Movimientos!$E$2:$E$312,Movimientos!$C$2:$C$312,$A21,Movimientos!$F$2:$F$312,3) -> 55.09 | E21: =SUMIFS(Movimientos!$E$2:$E$312,Movimientos!$C$2:$C$312,$A21,Movimientos!$F$2:$F$312,4) -> 201.08 | F21: =SUMIFS(Movimientos!$E$2:$E$312,Movimientos!$C$2:$C$312,$A21,Movimientos!$F$2:$F$312,5) -> 198.09 | G21: =SUMIFS(Movimientos!$E$2:$E$312,Movimientos!$C$2:$C$312,$A21,Movimientos!$F$2:$F$312,6) -> 141.17 | H21: =SUMIFS(Movimientos!$E$2:$E$312,Movimientos!$C$2:$C$312,$A21,Movimientos!$F$2:$F$312,7) -> 67.86 | I21: =SUMIFS(Movimientos!$E$2:$E$312,Movimientos!$C$2:$C$312,$A21,Movimientos!$F$2:$F$312,8) -> 188.01 | J21: =SUMIFS(Movimientos!$E$2:$E$312,Movimientos!$C$2:$C$312,$A21,Movimientos!$F$2:$F$312,9) -> 26.07 | K21: =SUMIFS(Movimientos!$E$2:$E$312,Movimientos!$C$2:$C$312,$A21,Movimientos!$F$2:$F$312,10) -> 77.43 | L21: =SUMIFS(Movimientos!$E$2:$E$312,Movimientos!$C$2:$C$312,$A21,Movimientos!$F$2:$F$312,11) -> 94.29 | M21: =SUMIFS(Movimientos!$E$2:$E$312,Movimientos!$C$2:$C$312,$A21,Movimientos!$F$2:$F$312,12) -> 79.2 | N21: =SUM(B21:M21) -> 1373.39 | O21: =AVERAGE(B21:M21) -> 114.44917 | P21: =N21/N$26 -> 0.052306707 | Q21: =SUMIF(Movimientos!$C$2:$C$312,$A21,Movimientos!$E$2:$E$312) -> 1373.39 | R21: =VLOOKUP($A21,Categorías!$A$2:$C$19,3,FALSE)*12 -> 1440 | S21: =N21-R21 -> -66.61 | T21: =IF(R21=0,0,N21/R21) -> 0.95374306
A22: Ropa | B22: =SUMIFS(Movimientos!$E$2:$E$312,Movimientos!$C$2:$C$312,$A22,Movimientos!$F$2:$F$312,1) -> 0 | C22: =SUMIFS(Movimientos!$E$2:$E$312,Movimientos!$C$2:$C$312,$A22,Movimientos!$F$2:$F$312,2) -> 105.03 | D22: =SUMIFS(Movimientos!$E$2:$E$312,Movimientos!$C$2:$C$312,$A22,Movimientos!$F$2:$F$312,3) -> 0 | E22: =SUMIFS(Movimientos!$E$2:$E$312,Movimientos!$C$2:$C$312,$A22,Movimientos!$F$2:$F$312,4) -> 192.19 | F22: =SUMIFS(Movimientos!$E$2:$E$312,Movimientos!$C$2:$C$312,$A22,Movimientos!$F$2:$F$312,5) -> 162.12 | G22: =SUMIFS(Movimientos!$E$2:$E$312,Movimientos!$C$2:$C$312,$A22,Movimientos!$F$2:$F$312,6) -> 84.43 | H22: =SUMIFS(Movimientos!$E$2:$E$312,Movimientos!$C$2:$C$312,$A22,Movimientos!$F$2:$F$312,7) -> 0 | I22: =SUMIFS(Movimientos!$E$2:$E$312,Movimientos!$C$2:$C$312,$A22,Movimientos!$F$2:$F$312,8) -> 186.12 | J22: =SUMIFS(Movimientos!$E$2:$E$312,Movimientos!$C$2:$C$312,$A22,Movimientos!$F$2:$F$312,9) -> 187.81 | K22: =SUMIFS(Movimientos!$E$2:$E$312,Movimientos!$C$2:$C$312,$A22,Movimientos!$F$2:$F$312,10) -> 113.3 | L22: =SUMIFS(Movimientos!$E$2:$E$312,Movimientos!$C$2:$C$312,$A22,Movimientos!$F$2:$F$312,11) -> 83.21 | M22: =SUMIFS(Movimientos!$E$2:$E$312,Movimientos!$C$2:$C$312,$A22,Movimientos!$F$2:$F$312,12) -> 0 | N22: =SUM(B22:M22) -> 1114.21 | O22: =AVERAGE(B22:M22) -> 92.850833 | P22: =N22/N$26 -> 0.04243562 | Q22: =SUMIF(Movimientos!$C$2:$C$312,$A22,Movimientos!$E$2:$E$312) -> 1114.21 | R22: =VLOOKUP($A22,Categorías!$A$2:$C$19,3,FALSE)*12 -> 1080 | S22: =N22-R22 -> 34.21 | T22: =IF(R22=0,0,N22/R22) -> 1.0316759
... A25: Regalos | B25: =SUMIFS(Movimientos!$E$2:$E$312,Movimientos!$C$2:$C$312,$A25,Movimientos!$F$2:$F$312,1) -> 0 | C25: =SUMIFS(Movimientos!$E$2:$E$312,Movimientos!$C$2:$C$312,$A25,Movimientos!$F$2:$F$312,2) -> 0 | D25: =SUMIFS(Movimientos!$E$2:$E$312,Movimientos!$C$2:$C$312,$A25,Movimientos!$F$2:$F$312,3) -> 40.75 | E25: =SUMIFS(Movimientos!$E$2:$E$312,Movimientos!$C$2:$C$312,$A25,Movimientos!$F$2:$F$312,4) -> 0 | F25: =SUMIFS(Movimientos!$E$2:$E$312,Movimientos!$C$2:$C$312,$A25,Movimientos!$F$2:$F$312,5) -> 0 | G25: =SUMIFS(Movimientos!$E$2:$E$312,Movimientos!$C$2:$C$312,$A25,Movimientos!$F$2:$F$312,6) -> 0 | H25: =SUMIFS(Movimientos!$E$2:$E$312,Movimientos!$C$2:$C$312,$A25,Movimientos!$F$2:$F$312,7) -> 0 | I25: =SUMIFS(Movimientos!$E$2:$E$312,Movimientos!$C$2:$C$312,$A25,Movimientos!$F$2:$F$312,8) -> 54.94 | J25: =SUMIFS(Movimientos!$E$2:$E$312,Movimientos!$C$2:$C$312,$A25,Movimientos!$F$2:$F$312,9) -> 23.16 | K25: =SUMIFS(Movimientos!$E$2:$E$312,Movimientos!$C$2:$C$312,$A25,Movimientos!$F$2:$F$312,10) -> 0 | L25: =SUMIFS(Movimientos!$E$2:$E$312,Movimientos!$C$2:$C$312,$A25,Movimientos!$F$2:$F$312,11) -> 0 | M25: =SUMIFS(Movimientos!$E$2:$E$312,Movimientos!$C$2:$C$312,$A25,Movimientos!$F$2:$F$312,12) -> 316.85 | N25: =SUM(B25:M25) -> 435.7 | O25: =AVERAGE(B25:M25) -> 36.308333 | P25: =N25/N$26 -> 0.016593999 | Q25: =SUMIF(Movimientos!$C$2:$C$312,$A25,Movimientos!$E$2:$E$312) -> 435.7 | R25: =VLOOKUP($A25,Categorías!$A$2:$C$19,3,FALSE)*12 -> 480 | S25: =N25-R25 -> -44.3 | T25: =IF(R25=0,0,N25/R25) -> 0.90770833
A26: Total gastos | B26: =SUM(B11:B25) -> 2079.36 | C26: =SUM(C11:C25) -> 1828.91 | D26: =SUM(D11:D25) -> 2595.76 | E26: =SUM(E11:E25) -> 2329.1 | F26: =SUM(F11:F25) -> 2326.15 | G26: =SUM(G11:G25) -> 1937.92 | H26: =SUM(H11:H25) -> 2205.39 | I26: =SUM(I11:I25) -> 2076.42 | ... N26: =SUM(N11:N25) -> 26256.48 | O26: =AVERAGE(B26:M26) -> 2188.04 | P26: =SUM(P11:P25) -> 1 | Q26: =SUM(Q11:Q25) -> 26256.48 | R26: =SUM(R11:R25) -> 28738.8 | S26: =N26-R26 -> -2482.32 | T26: =IF(R26=0,0,N26/R26) -> 0.91362479
A28: Ahorro neto | B28: =B8-B26 -> 2544.26 | C28: =C8-C26 -> 2880.05 | D28: =D8-D26 -> 2005.54 | E28: =E8-E26 -> 2100.9 | F28: =F8-F26 -> 2103.85 | G28: =G8-G26 -> 4942.08 | H28: =H8-H26 -> 4204.61 | I28: =I8-I26 -> 2353.58 | ... N28: =N8-N26 -> 36953.09
A29: Tasa de ahorro | B29: =IF(B8=0,0,B28/B8) -> 0.55027446 | C29: =IF(C8=0,0,C28/C8) -> 0.61161063 | D29: =IF(D8=0,0,D28/D8) -> 0.43586378 | E29: =IF(E8=0,0,E28/E8) -> 0.47424379 | F29: =IF(F8=0,0,F28/F8) -> 0.47490971 | G29: =IF(G8=0,0,G28/G8) -> 0.71832558 | H29: =IF(H8=0,0,H28/H8) -> 0.6559454 | I29: =IF(I8=0,0,I28/I8) -> 0.53128217 | ... N29: =IF(N8=0,0,N28/N8) -> 0.58461227

Sheet Movimientos
A1: Fecha | B1: Concepto | C1: Categoría | D1: Tipo | E1: Importe | F1: Mes
A2: 45658 | B2: Recibo hipoteca BBVA | C2: Hipoteca | D2: Gasto | E2: 780 | F2: =MONTH(A2) -> 1
A3: 45658 | B3: Restaurante El Puerto | C3: Restaurantes | D3: Gasto | E3: 51.79 | F3: =MONTH(A3) -> 1
A4: 45659 | B4: Academia de inglés | C4: Educación | D4: Gasto | E4: 60 | F4: =MONTH(A4) -> 1
A5: 45660 | B5: Movistar fibra + móvil | C5: Internet y móvil | D5: Gasto | E5: 59.9 | F5: =MONTH(A5) -> 1
A6: 45661 | B6: Dentista | C6: Salud | D6: Gasto | E6: 42.24 | F6: =MONTH(A6) -> 1
A7: 45662 | B7: Cuota comunidad propietarios | C7: Comunidad | D7: Gasto | E7: 65 | F7: =MONTH(A7) -> 1
A8: 45664 | B8: Gasolina Repsol | C8: Transporte | D8: Gasto | E8: 43.18 | F8: =MONTH(A8) -> 1
A9: 45667 | B9: Seguro de vida | C9: Seguros | D9: Gasto | E9: 35 | F9: =MONTH(A9) -> 1
A10: 45667 | B10: Carrefour | C10: Supermercado | D10: Gasto | E10: 36.33 | F10: =MONTH(A10) -> 1
A11: 45668 | B11: Telepizza | C11: Restaurantes | D11: Gasto | E11: 48.77 | F11: =MONTH(A11) -> 1
A12: 45669 | B12: Iberdrola Clientes S.A.U. | C12: Luz | D12: Gasto | E12: 60.15 | F12: =MONTH(A12) -> 1
A13: 45670 | B13: Alcampo | C13: Supermercado | D13: Gasto | E13: 106.74 | F13: =MONTH(A13) -> 1
... A312: 46019 | B312: Restaurante El Puerto | C312: Restaurantes | D312: Gasto | E312: 39.4 | F312: =MONTH(A312) -> 12

Sheet Categorías
A1: Categoría | B1: Tipo | C1: Presupuesto mensual
A2: Nómina | B2: Ingreso | C2: 2450
A3: Nómina pareja | B3: Ingreso | C3: 1980
A4: Extras | B4: Ingreso | C4: 150
A5: Hipoteca | B5: Gasto | C5: 780
A6: Comunidad | B6: Gasto | C6: 65
A7: Luz | B7: Gasto | C7: 72
A8: Agua | B8: Gasto | C8: 28
A9: Gas | B9: Gasto | C9: 45
A10: Internet y móvil | B10: Gasto | C10: 59.9
A11: Supermercado | B11: Gasto | C11: 520
A12: Transporte | B12: Gasto | C12: 140
A13: Seguros | B13: Gasto | C13: 85
... A19: Regalos | B19: Gasto | C19: 40
